lektor_slugify.py
lektor_slugify-0.4.dist-info/LICENSE
lektor_slugify-0.4.dist-info/METADATA
lektor_slugify-0.4.dist-info/WHEEL
lektor_slugify-0.4.dist-info/entry_points.txt
lektor_slugify-0.4.dist-info/top_level.txt
lektor_slugify-0.4.dist-info/RECORD
