Metadata-Version: 2.1
Name: lektor-slugify
Version: 0.4
Summary: Lektor plugin that adds a slugify Jinja filter.
Home-page: https://github.com/terminal-labs/lektor-slugify
Author: Terminal Labs, Michael Verhulst, Joseph Nix
Author-email: solutions@terminallabs.com
License: BSD-3-Clause
Keywords: Lektor plugin static-site slug jinja2 jinja filter
Platform: UNKNOWN
Classifier: Environment :: Plugins
Classifier: Environment :: Web Environment
Classifier: Framework :: Lektor
Classifier: License :: OSI Approved :: BSD License
Requires-Dist: python-slugify (>=1.2.6)
